LICENSE.txt
README.md
setup.py
biptrader/__init__.py
biptrader/download_exchange.py
biptrader/my_exchange.py
biptrader/util.py
biptrader.egg-info/PKG-INFO
biptrader.egg-info/SOURCES.txt
biptrader.egg-info/dependency_links.txt
biptrader.egg-info/requires.txt
biptrader.egg-info/top_level.txt
tests/__init__.py
tests/test_download_exchange.py