Metadata-Version: 2.1
Name: biptrader
Version: 0.1.3
Summary: cryptocurrency trading helper library
Home-page: https://github.com/adramazany/biptrader
Author: Adel Ramezani
Author-email: adramazany@gmail.com
License: MIT
Keywords: cryptocurrency kucoin technical-analysis
License-File: LICENSE.txt
